odoo10_addon_account_analytic_distribution-10.0.1.0.0-py2.7-nspkg.pth
odoo/addons/account_analytic_distribution/README.rst
odoo/addons/account_analytic_distribution/__init__.py
odoo/addons/account_analytic_distribution/__manifest__.py
odoo/addons/account_analytic_distribution/i18n/es.po
odoo/addons/account_analytic_distribution/models/__init__.py
odoo/addons/account_analytic_distribution/models/account_analytic_distribution.py
odoo/addons/account_analytic_distribution/models/account_invoice.py
odoo/addons/account_analytic_distribution/models/account_invoice_line.py
odoo/addons/account_analytic_distribution/models/account_move_line.py
odoo/addons/account_analytic_distribution/models/res_company.py
odoo/addons/account_analytic_distribution/security/ir.model.access.csv
odoo/addons/account_analytic_distribution/static/description/icon.png
odoo/addons/account_analytic_distribution/tests/__init__.py
odoo/addons/account_analytic_distribution/tests/test_analytic_distribution.py
odoo/addons/account_analytic_distribution/views/account_analytic_distribution_view.xml
odoo/addons/account_analytic_distribution/views/account_invoice_view.xml
odoo/addons/account_analytic_distribution/views/account_move_line_view.xml
odoo/addons/account_analytic_distribution/views/account_move_view.xml
odoo/addons/account_analytic_distribution/views/res_company_view.xml
odoo10_addon_account_analytic_distribution-10.0.1.0.0.dist-info/DESCRIPTION.rst
odoo10_addon_account_analytic_distribution-10.0.1.0.0.dist-info/METADATA
odoo10_addon_account_analytic_distribution-10.0.1.0.0.dist-info/RECORD
odoo10_addon_account_analytic_distribution-10.0.1.0.0.dist-info/WHEEL
odoo10_addon_account_analytic_distribution-10.0.1.0.0.dist-info/metadata.json
odoo10_addon_account_analytic_distribution-10.0.1.0.0.dist-info/namespace_packages.txt
odoo10_addon_account_analytic_distribution-10.0.1.0.0.dist-info/top_level.txt
